dz_dynamodb/__init__.py
dz_dynamodb/deserialize.py
dz_dynamodb/discover.py
dz_dynamodb/dynamodb.py
dz_dynamodb/sync.py
dz_dynamodb/sync_strategies/__init__.py
dz_dynamodb/sync_strategies/full_table.py
dz_dynamodb/sync_strategies/log_based.py
tap_dz_dynamodb/__init__.py
tap_dz_dynamodb/deserialize.py
tap_dz_dynamodb/discover.py
tap_dz_dynamodb/dynamodb.py
tap_dz_dynamodb/sync.py
tap_dz_dynamodb/sync_strategies/__init__.py
tap_dz_dynamodb/sync_strategies/full_table.py
tap_dz_dynamodb/sync_strategies/log_based.py
dz_dynamodb-1.3.9.dist-info/LICENSE
dz_dynamodb-1.3.9.dist-info/METADATA
dz_dynamodb-1.3.9.dist-info/WHEEL
dz_dynamodb-1.3.9.dist-info/entry_points.txt
dz_dynamodb-1.3.9.dist-info/top_level.txt
dz_dynamodb-1.3.9.dist-info/RECORD
